LICENSE.txt
MANIFEST.in
README.md
setup.py
jk_xmlparser/TagBegin.py
jk_xmlparser/TagComment.py
jk_xmlparser/TagEnd.py
jk_xmlparser/TagSpecial.py
jk_xmlparser/TagXMLHeader.py
jk_xmlparser/XMLDOMParseException.py
jk_xmlparser/XMLDOMParser.py
jk_xmlparser/XMLDOMParser_old.py
jk_xmlparser/XMLTokenizerImpl.py
jk_xmlparser/__init__.py
jk_xmlparser.egg-info/PKG-INFO
jk_xmlparser.egg-info/SOURCES.txt
jk_xmlparser.egg-info/dependency_links.txt
jk_xmlparser.egg-info/not-zip-safe
jk_xmlparser.egg-info/requires.txt
jk_xmlparser.egg-info/top_level.txt