Metadata-Version: 2.1
Name: jk-xmlparser
Version: 0.2019.4.10
Summary: This python module parses XML (and HTML) files.
Home-page: https://github.com/jkpubsrc/python-module-jk-xmlparser
Author: Jürgen Knauth
Author-email: pubsrc@binary-overflow.de
License: Apache 2.0
Download-URL: https://github.com/jkpubsrc/python-module-jk-xmlparser/tarball/0.2019.4.10
Keywords: parsing
Platform: UNKNOWN
Classifier: Development Status :: 4 - Beta
Classifier: License :: OSI Approved :: Apache Software License
